izaber_wamp/__init__.py
izaber_wamp-3.0.20231125.dist-info/METADATA
izaber_wamp-3.0.20231125.dist-info/WHEEL
izaber_wamp-3.0.20231125.dist-info/RECORD
